{
  "success": true,
  "fetched_at": "2026-05-01T04:25:51.277102",
  "ticker": "1893",
  "ticker_full": "1893.T",
  "company_name": "PENTA OCEAN CONSTRUCTION",
  "analyst_recommendations": {
    "has_data": true,
    "period": "3",
    "strong_buy": 3,
    "buy": 3,
    "hold": 0,
    "sell": 0,
    "strong_sell": 0,
    "total_analysts": 6,
    "recommendation_key": "strong_buy",
    "recommendation_mean": 1.5
  },
  "target_prices": {
    "has_data": true,
    "current": 1773.5,
    "high": 2600.0,
    "low": 1900.0,
    "mean": 2220.0,
    "median": 2100.0
  },
  "earnings_dates": {
    "has_data": true,
    "next_earnings": {
      "date": "2026-05-08",
      "eps_estimate": null,
      "eps_actual": null,
      "surprise_pct": null
    },
    "future_count": 1,
    "past_earnings": [
      {
        "date": "2020-05-11",
        "eps_estimate": 15.9,
        "eps_actual": 19.2,
        "surprise_pct": 20.75
      }
    ]
  },
  "shareholders": {
    "has_data": true,
    "insider_pct": 3.37,
    "institution_pct": 45.87,
    "major_holders": [
      {
        "label": "",
        "value": 3.37
      },
      {
        "label": "",
        "value": 45.87
      },
      {
        "label": "",
        "value": 47.47
      },
      {
        "label": "",
        "value": 115.0
      }
    ],
    "institutional_holders": [
      {
        "holder": "Legato Capital Management LLC",
        "shares": 55717,
        "date_reported": "2022-06-30",
        "pct_held": 0.02,
        "pct_change": 1.0,
        "value": 98814099
      }
    ],
    "mutualfund_holders": [
      {
        "holder": "American Century ETF Trust-Avantis International Small Cap Value ETF",
        "shares": 7059200,
        "date_reported": "2026-03-31",
        "pct_held": 2.47,
        "pct_change": 0.0,
        "value": 12519491200
      },
      {
        "holder": "VANGUARD STAR FUNDS-Vanguard Total International Stock Index Fund",
        "shares": 4054919,
        "date_reported": "2026-01-31",
        "pct_held": 1.42,
        "pct_change": 0.74,
        "value": 7191398846
      },
      {
        "holder": "T. ROWE PRICE Intl Fd.S, INC.-T. Rowe Price Intl Discovery Fd.",
        "shares": 3101800,
        "date_reported": "2026-01-31",
        "pct_held": 1.08,
        "pct_change": -3.69,
        "value": 5501042300
      },
      {
        "holder": "VANGUARD TAX-MANAGED FUNDS-Vanguard Developed Markets Index Fund",
        "shares": 2522651,
        "date_reported": "2025-12-31",
        "pct_held": 0.88,
        "pct_change": 0.48,
        "value": 4473921548
      },
      {
        "holder": "iShares Trust-iShares Core MSCI EAFE ETF",
        "shares": 2067900,
        "date_reported": "2026-03-31",
        "pct_held": 0.72,
        "pct_change": 1.0,
        "value": 3667420650
      },
      {
        "holder": "DFA INVESTMENT TRUST CO-The Japanese Small Company Series",
        "shares": 1498652,
        "date_reported": "2026-01-31",
        "pct_held": 0.52,
        "pct_change": -2.12,
        "value": 2657859322
      },
      {
        "holder": "DFA INVESTMENT DIMENSIONS GROUP INC-Intl Core Eqy. 2 PORT.",
        "shares": 1444700,
        "date_reported": "2026-01-31",
        "pct_held": 0.51,
        "pct_change": 0.0,
        "value": 2562175450
      },
      {
        "holder": "iShares Trust-iShares MSCI EAFE Small-Cap ETF",
        "shares": 1072500,
        "date_reported": "2026-03-31",
        "pct_held": 0.37,
        "pct_change": 1.23,
        "value": 1902078750
      },
      {
        "holder": "VANGUARD Intl Eqy. INDEX Fd.S-Vanguard FTSE All-World ex-US Small-Cap ",
        "shares": 972300,
        "date_reported": "2026-01-31",
        "pct_held": 0.34,
        "pct_change": 3.28,
        "value": 1724374050
      },
      {
        "holder": "GMO TRUST-GMO-Usonian Japan Value Creation Fund",
        "shares": 754900,
        "date_reported": "2026-02-28",
        "pct_held": 0.26,
        "pct_change": 4.95,
        "value": 1338815150
      }
    ]
  }
}