{
  "success": true,
  "fetched_at": "2026-06-01T05:07:03.480707",
  "ticker": "2734",
  "ticker_full": "2734.T",
  "company_name": "SALA CORPORATION",
  "analyst_recommendations": {
    "has_data": true,
    "recommendation_key": "none",
    "recommendation_mean": null,
    "total_analysts": null,
    "strong_buy": null,
    "buy": null,
    "hold": null,
    "sell": null,
    "strong_sell": null
  },
  "target_prices": {
    "has_data": true,
    "current": 971.0,
    "high": null,
    "low": null,
    "mean": null,
    "median": null
  },
  "earnings_dates": {
    "has_data": false,
    "error": "['Earnings Date']"
  },
  "shareholders": {
    "has_data": true,
    "insider_pct": 14.73,
    "institution_pct": 26.54,
    "major_holders": [
      {
        "label": "",
        "value": 14.73
      },
      {
        "label": "",
        "value": 26.54
      },
      {
        "label": "",
        "value": 31.12
      },
      {
        "label": "",
        "value": 45.0
      }
    ],
    "institutional_holders": [],
    "mutualfund_holders": []
  }
}