{
  "success": true,
  "fetched_at": "2026-04-01T03:29:28.310039",
  "ticker": "5976",
  "ticker_full": "5976.T",
  "company_name": "NETUREN CO LTD",
  "analyst_recommendations": {
    "has_data": true,
    "recommendation_key": "none",
    "recommendation_mean": null,
    "total_analysts": null,
    "strong_buy": null,
    "buy": null,
    "hold": null,
    "sell": null,
    "strong_sell": null
  },
  "target_prices": {
    "has_data": true,
    "current": 1284.0,
    "high": null,
    "low": null,
    "mean": null,
    "median": null
  },
  "earnings_dates": {
    "has_data": false
  },
  "shareholders": {
    "has_data": true,
    "insider_pct": 18.58,
    "institution_pct": 27.05,
    "major_holders": [
      {
        "label": "",
        "value": 18.58
      },
      {
        "label": "",
        "value": 27.05
      },
      {
        "label": "",
        "value": 33.22
      },
      {
        "label": "",
        "value": 36.0
      }
    ],
    "institutional_holders": [],
    "mutualfund_holders": []
  }
}