{
  "success": true,
  "fetched_at": "2026-01-11T06:35:32.451407",
  "ticker": "7740",
  "ticker_full": "7740.T",
  "company_name": "TAMRON CO LTD",
  "analyst_recommendations": {
    "has_data": true,
    "period": "2",
    "strong_buy": 0,
    "buy": 2,
    "hold": 2,
    "sell": 0,
    "strong_sell": 0,
    "total_analysts": 4,
    "recommendation_key": "none",
    "recommendation_mean": null
  },
  "target_prices": {
    "has_data": true,
    "current": 1052.0,
    "high": 1300.0,
    "low": 913.0,
    "mean": 1090.75,
    "median": 1075.0
  },
  "earnings_dates": {
    "has_data": false,
    "error": "Missing optional dependency 'lxml'.  Use pip or conda to install lxml."
  },
  "shareholders": {
    "has_data": true,
    "insider_pct": 20.43,
    "institution_pct": 41.54,
    "major_holders": [
      {
        "label": "",
        "value": 20.43
      },
      {
        "label": "",
        "value": 41.54
      },
      {
        "label": "",
        "value": 52.21
      },
      {
        "label": "",
        "value": 82.0
      }
    ],
    "institutional_holders": [
      {
        "holder": "VANGUARD STAR FUNDS-Vanguard Total International Stock Index Fund",
        "shares": 1804924,
        "date_reported": "2025-10-31",
        "pct_held": 1.06,
        "pct_change": 1.81,
        "value": 1898780048
      },
      {
        "holder": "VANGUARD TAX-MANAGED FUNDS-Vanguard Developed Markets Index Fund",
        "shares": 1143128,
        "date_reported": "2025-09-30",
        "pct_held": 0.67,
        "pct_change": 0.0,
        "value": 1202570656
      },
      {
        "holder": "iShares Trust-iShares Core MSCI EAFE ETF",
        "shares": 958700,
        "date_reported": "2025-11-30",
        "pct_held": 0.56,
        "pct_change": 1.09,
        "value": 1008552400
      },
      {
        "holder": "Old Westbury Funds Inc-Old Westbury Small & Mid Cap Strategies Fund",
        "shares": 932000,
        "date_reported": "2025-10-31",
        "pct_held": 0.55,
        "pct_change": 0.0,
        "value": 980464000
      },
      {
        "holder": "DFA INVESTMENT TRUST CO-The Japanese Small Company Series",
        "shares": 824800,
        "date_reported": "2025-10-31",
        "pct_held": 0.48,
        "pct_change": 0.0,
        "value": 867689600
      },
      {
        "holder": "DFA INVESTMENT DIMENSIONS GROUP INC-Intl Core Eqy. 2 PORT.",
        "shares": 626000,
        "date_reported": "2025-10-31",
        "pct_held": 0.37,
        "pct_change": 0.0,
        "value": 658552000
      },
      {
        "holder": "iShares Trust-iShares MSCI EAFE Small-Cap ETF",
        "shares": 475200,
        "date_reported": "2025-10-31",
        "pct_held": 0.28,
        "pct_change": 5.11,
        "value": 499910400
      },
      {
        "holder": "VANGUARD Intl Eqy. INDEX Fd.S-Vanguard FTSE All-World ex-US Small-Cap ",
        "shares": 434000,
        "date_reported": "2025-10-31",
        "pct_held": 0.25,
        "pct_change": 3.04,
        "value": 456568000
      },
      {
        "holder": "WisdomTree Trust-WisdomTree Japan Hedged Equity Fund",
        "shares": 375700,
        "date_reported": "2025-09-30",
        "pct_held": 0.22,
        "pct_change": 28.66,
        "value": 395236400
      },
      {
        "holder": "iShares Trust-iShares Core MSCI Total International Stock ETF",
        "shares": 365600,
        "date_reported": "2025-11-30",
        "pct_held": 0.21,
        "pct_change": 0.0,
        "value": 384611200
      }
    ],
    "mutualfund_holders": []
  }
}