{
  "success": true,
  "fetched_at": "2026-04-01T03:59:38.054765",
  "ticker": "8136",
  "ticker_full": "8136.T",
  "company_name": "SANRIO CO LTD",
  "analyst_recommendations": {
    "has_data": true,
    "period": "3",
    "strong_buy": 2,
    "buy": 7,
    "hold": 2,
    "sell": 0,
    "strong_sell": 0,
    "total_analysts": 11,
    "recommendation_key": "strong_buy",
    "recommendation_mean": 1.45455
  },
  "target_prices": {
    "has_data": true,
    "current": 985.0,
    "high": 1860.0,
    "low": 1200.0,
    "mean": 1516.1909,
    "median": 1500.0
  },
  "earnings_dates": {
    "has_data": false,
    "error": "['Earnings Date']"
  },
  "shareholders": {
    "has_data": true,
    "insider_pct": 18.41,
    "institution_pct": 43.38,
    "major_holders": [
      {
        "label": "",
        "value": 18.41
      },
      {
        "label": "",
        "value": 43.38
      },
      {
        "label": "",
        "value": 53.16
      },
      {
        "label": "",
        "value": 292.0
      }
    ],
    "institutional_holders": [
      {
        "holder": "Pacer Advisors, Inc.",
        "shares": 11875,
        "date_reported": "2025-12-31",
        "pct_held": 0.0,
        "pct_change": -2.66,
        "value": 11696875
      }
    ],
    "mutualfund_holders": [
      {
        "holder": "VANGUARD STAR FUNDS-Vanguard Total International Stock Index Fund",
        "shares": 13837575,
        "date_reported": "2025-10-31",
        "pct_held": 1.08,
        "pct_change": 10.44,
        "value": 13630011375
      },
      {
        "holder": "VANGUARD TAX-MANAGED FUNDS-Vanguard Developed Markets Index Fund",
        "shares": 8970830,
        "date_reported": "2025-12-31",
        "pct_held": 0.7,
        "pct_change": 1.99,
        "value": 8836267550
      },
      {
        "holder": "T. ROWE PRICE Intl Fd.S, INC.-T. Rowe Price Intl Stock Fd.",
        "shares": 6768500,
        "date_reported": "2026-01-31",
        "pct_held": 0.53,
        "pct_change": 1.0,
        "value": 6666972500
      },
      {
        "holder": "MORGAN STANLEY Inst. Fd. INC-Intl Advantage PORT.",
        "shares": 6464500,
        "date_reported": "2025-12-31",
        "pct_held": 0.51,
        "pct_change": 50.35,
        "value": 6367532500
      },
      {
        "holder": "iShares Trust-iShares Core MSCI EAFE ETF",
        "shares": 6156000,
        "date_reported": "2026-01-31",
        "pct_held": 0.48,
        "pct_change": 0.62,
        "value": 6063660000
      },
      {
        "holder": "Capital Group Global Growth Equity ETF",
        "shares": 4945500,
        "date_reported": "2025-11-30",
        "pct_held": 0.39,
        "pct_change": 10.11,
        "value": 4871317500
      },
      {
        "holder": "AMERICAN FUNDS INSURANCE SERIES-Global Growth Fund",
        "shares": 4561500,
        "date_reported": "2025-12-31",
        "pct_held": 0.36,
        "pct_change": 0.0,
        "value": 4493077500
      },
      {
        "holder": "T. ROWE PRICE COMMUNICATIONS & TECHNOLOGY Fd., INC.-T. Rowe Price Comm",
        "shares": 4184000,
        "date_reported": "2025-12-31",
        "pct_held": 0.33,
        "pct_change": -1.66,
        "value": 4121240000
      },
      {
        "holder": "Fidelity Concord Street Trust-Fidelity International Index Fund",
        "shares": 3221545,
        "date_reported": "2026-01-31",
        "pct_held": 0.25,
        "pct_change": 0.8,
        "value": 3173221825
      },
      {
        "holder": "iShares, Inc.-iShares MSCI Japan ETF",
        "shares": 3098500,
        "date_reported": "2026-01-31",
        "pct_held": 0.24,
        "pct_change": 1.06,
        "value": 3052022500
      }
    ]
  }
}