{
  "success": true,
  "fetched_at": "2026-06-01T05:17:43.208399",
  "ticker": "8968",
  "ticker_full": "8968.T",
  "company_name": "FUKUOKA REIT CORP",
  "analyst_recommendations": {
    "has_data": true,
    "period": "2",
    "strong_buy": 0,
    "buy": 1,
    "hold": 1,
    "sell": 1,
    "strong_sell": 0,
    "total_analysts": 3,
    "recommendation_key": "none",
    "recommendation_mean": null
  },
  "target_prices": {
    "has_data": true,
    "current": 169400.0,
    "high": 220000.0,
    "low": 192000.0,
    "mean": 200500.0,
    "median": 195000.0
  },
  "earnings_dates": {
    "has_data": true,
    "next_earnings": {
      "date": "2026-10-15",
      "eps_estimate": null,
      "eps_actual": null,
      "surprise_pct": null
    },
    "future_count": 1,
    "past_earnings": []
  },
  "shareholders": {
    "has_data": true,
    "insider_pct": 18.94,
    "institution_pct": 34.84,
    "major_holders": [
      {
        "label": "",
        "value": 18.94
      },
      {
        "label": "",
        "value": 34.84
      },
      {
        "label": "",
        "value": 42.98
      },
      {
        "label": "",
        "value": 87.0
      }
    ],
    "institutional_holders": [],
    "mutualfund_holders": []
  }
}