{
  "success": true,
  "fetched_at": "2026-06-07T04:29:04.666508",
  "ticker": "157A",
  "ticker_full": "157A.T",
  "company_name": "GREEN MONSTER INC",
  "company_info": {
    "name_en": "GREEN MONSTER INC",
    "long_name": "",
    "sector": "Technology",
    "industry": "Software - Application",
    "website": "https://www.greenmonster.co.jp",
    "employees": 43,
    "country": "Japan",
    "city": "Shibuya",
    "address": "1-4-9 Jinnan",
    "description": "Green Monster Inc. provides investment learning support services in Japan. The company offers smartphone apps that allow hands-on learning about FX (*1), stock investment, and asset formation through game-like demo trading and simulations. It also provides financial education, life planning proposals, home purchasing, and advice on inheritance planning for corporations, individuals, and housing. The company was incorporated in 2013 and is headquartered in Shibuya, Japan."
  },
  "price_trend": {
    "ma_5": {
      "ma_value": 894.6,
      "deviation": -0.51,
      "trend": "down"
    },
    "ma_25": {
      "ma_value": 963.04,
      "deviation": -7.58,
      "trend": "down"
    },
    "ma_75": {
      "ma_value": 1071.35,
      "deviation": -16.93,
      "trend": "down"
    },
    "ma_200": {
      "ma_value": 854.22,
      "deviation": 4.19,
      "trend": "up"
    }
  },
  "financials": {
    "years": [
      {
        "year": 2025,
        "revenue": 2006859000.0,
        "revenue_fmt": "¥20億",
        "gross_profit": 709932000.0,
        "gross_profit_fmt": "¥7億",
        "operating_income": 123675000.0,
        "operating_income_fmt": "¥1億",
        "ebit": 79258000.0,
        "ebit_fmt": "¥79.3M",
        "net_income": 32652000.0,
        "net_income_fmt": "¥32.7M",
        "eps": 9.86,
        "operating_margin": 6.16,
        "total_assets": 1821541000.0,
        "total_assets_fmt": "¥18億",
        "total_equity": 1430969000.0,
        "total_equity_fmt": "¥14億",
        "total_debt": 50794000.0,
        "total_debt_fmt": "¥50.8M",
        "total_cash": 1185144000.0,
        "total_cash_fmt": "¥12億",
        "equity_ratio": 78.56,
        "de_ratio": 0.04,
        "current_ratio": 4.69,
        "operating_cf": -6909000.0,
        "operating_cf_fmt": "-¥6.9M",
        "investing_cf": -215376000.0,
        "investing_cf_fmt": "-¥2億",
        "financing_cf": -82640000.0,
        "financing_cf_fmt": "-¥82.6M",
        "free_cf": -25278000.0,
        "free_cf_fmt": "-¥25.3M",
        "net_margin": 1.63,
        "roe": 2.28,
        "roa": 1.79
      },
      {
        "year": 2024,
        "revenue": 1957473000.0,
        "revenue_fmt": "¥20億",
        "gross_profit": 622260000.0,
        "gross_profit_fmt": "¥6億",
        "operating_income": 231030000.0,
        "operating_income_fmt": "¥2億",
        "ebit": 232487000.0,
        "ebit_fmt": "¥2億",
        "net_income": 156190000.0,
        "net_income_fmt": "¥2億",
        "eps": 54.37,
        "operating_margin": 11.8,
        "total_assets": 1850191000.0,
        "total_assets_fmt": "¥19億",
        "total_equity": 1472223000.0,
        "total_equity_fmt": "¥15億",
        "total_debt": 60802000.0,
        "total_debt_fmt": "¥60.8M",
        "total_cash": 1490070000.0,
        "total_cash_fmt": "¥15億",
        "equity_ratio": 79.57,
        "de_ratio": 0.04,
        "current_ratio": 5.82,
        "operating_cf": 168752000.0,
        "operating_cf_fmt": "¥2億",
        "investing_cf": -74331000.0,
        "investing_cf_fmt": "-¥74.3M",
        "financing_cf": 658592000.0,
        "financing_cf_fmt": "¥7億",
        "free_cf": 114362000.0,
        "free_cf_fmt": "¥1億",
        "net_margin": 7.98,
        "roe": 10.61,
        "roa": 8.44
      },
      {
        "year": 2023,
        "revenue": 1711553000.0,
        "revenue_fmt": "¥17億",
        "gross_profit": 485106000.0,
        "gross_profit_fmt": "¥5億",
        "operating_income": 164838000.0,
        "operating_income_fmt": "¥2億",
        "ebit": 170428000.0,
        "ebit_fmt": "¥2億",
        "net_income": 121585000.0,
        "net_income_fmt": "¥1億",
        "eps": 49.83,
        "operating_margin": 9.63,
        "total_assets": 1065475000.0,
        "total_assets_fmt": "¥11億",
        "total_equity": 639832000.0,
        "total_equity_fmt": "¥6億",
        "total_debt": 78410000.0,
        "total_debt_fmt": "¥78.4M",
        "total_cash": 737057000.0,
        "total_cash_fmt": "¥7億",
        "equity_ratio": 60.05,
        "de_ratio": 0.12,
        "current_ratio": 2.94,
        "operating_cf": 255429000.0,
        "operating_cf_fmt": "¥3億",
        "investing_cf": 3331000.0,
        "investing_cf_fmt": "¥3.3M",
        "financing_cf": -27396000.0,
        "financing_cf_fmt": "-¥27.4M",
        "free_cf": 250951000.0,
        "free_cf_fmt": "¥3億",
        "net_margin": 7.1,
        "roe": 19.0,
        "roa": 11.41
      },
      {
        "year": 2022,
        "revenue": 1397007000.0,
        "revenue_fmt": "¥14億",
        "gross_profit": 278224000.0,
        "gross_profit_fmt": "¥3億",
        "operating_income": 52818000.0,
        "operating_income_fmt": "¥52.8M",
        "ebit": 51923000.0,
        "ebit_fmt": "¥51.9M",
        "net_income": 38752000.0,
        "net_income_fmt": "¥38.8M",
        "eps": 12.15,
        "operating_margin": 3.78,
        "total_assets": 810145000.0,
        "total_assets_fmt": "¥8億",
        "total_equity": 518246000.0,
        "total_equity_fmt": "¥5億",
        "total_debt": 97506000.0,
        "total_debt_fmt": "¥97.5M",
        "total_cash": 505692000.0,
        "total_cash_fmt": "¥5億",
        "equity_ratio": 63.97,
        "de_ratio": 0.19,
        "current_ratio": 3.43,
        "operating_cf": -16277000.0,
        "operating_cf_fmt": "-¥16.3M",
        "investing_cf": -53811000.0,
        "investing_cf_fmt": "-¥53.8M",
        "financing_cf": -26664000.0,
        "financing_cf_fmt": "-¥26.7M",
        "free_cf": -20088000.0,
        "free_cf_fmt": "-¥20.1M",
        "net_margin": 2.77,
        "roe": 7.48,
        "roa": 4.78
      }
    ],
    "has_data": true
  },
  "dividends": {
    "history": [
      {
        "year": 2024,
        "amount": 10.0
      },
      {
        "year": 2025,
        "amount": 10.0
      }
    ],
    "latest": 10.0,
    "has_data": true
  }
}