{
  "success": true,
  "fetched_at": "2026-06-14T04:43:55.109581",
  "ticker": "4052",
  "ticker_full": "4052.T",
  "company_name": "FICHA INC",
  "company_info": {
    "name_en": "FICHA INC",
    "long_name": "Ficha Inc.",
    "sector": "Technology",
    "industry": "Software - Application",
    "website": "https://ficha.jp",
    "employees": 31,
    "country": "Japan",
    "city": "Toshima",
    "address": "Sunshine 60",
    "description": "Ficha Inc. develops and sells image recognition software for car cameras in Japan. The company provides object detection software for the Advanced Driver Assistance System (ADAS); the Driver Monitoring System (DMS), a system for monitoring the driver's driving condition with an in-vehicle camera to prevent dangerous driving and accidents; and Occupant Monitoring System (OMS), a system monitors the condition of passengers using in-vehicle cameras, detects dangerous postures, dispenses airbags, and prevents children from being left behind. It also offers AI-OCR, a software that detects character areas from texts on various forms, as well as recognizes printed and handwritten characters; and various solutions for traffic monitoring, infrastructure control, people flow analysis, etc. Ficha Inc. was incorporated in 2005 and is headquartered in Toshima, Japan."
  },
  "price_trend": {
    "ma_5": {
      "ma_value": 257.8,
      "deviation": -3.8,
      "trend": "down"
    },
    "ma_25": {
      "ma_value": 262.36,
      "deviation": -5.47,
      "trend": "down"
    },
    "ma_75": {
      "ma_value": 288.84,
      "deviation": -14.14,
      "trend": "down"
    },
    "ma_200": {
      "ma_value": 307.3,
      "deviation": -19.3,
      "trend": "down"
    }
  },
  "financials": {
    "years": [
      {
        "year": 2025,
        "revenue": 0,
        "revenue_fmt": "N/A",
        "gross_profit": 0,
        "gross_profit_fmt": "N/A",
        "operating_income": 0,
        "operating_income_fmt": "N/A",
        "ebit": 0,
        "ebit_fmt": "N/A",
        "net_income": 0,
        "net_income_fmt": "N/A",
        "eps": -6.6,
        "operating_margin": 0,
        "total_assets": 0,
        "total_assets_fmt": "N/A",
        "total_equity": 0,
        "total_equity_fmt": "N/A",
        "total_debt": 0,
        "total_debt_fmt": "N/A",
        "total_cash": 0,
        "total_cash_fmt": "N/A",
        "equity_ratio": 0,
        "de_ratio": 0,
        "current_ratio": 0,
        "operating_cf": 0,
        "operating_cf_fmt": "N/A",
        "investing_cf": 0,
        "investing_cf_fmt": "N/A",
        "financing_cf": 0,
        "financing_cf_fmt": "N/A",
        "free_cf": 0,
        "free_cf_fmt": "N/A",
        "net_margin": 0,
        "roe": 0,
        "roa": 0
      },
      {
        "year": 2024,
        "revenue": 494209000.0,
        "revenue_fmt": "¥5億",
        "gross_profit": 330865000.0,
        "gross_profit_fmt": "¥3億",
        "operating_income": -3567000.0,
        "operating_income_fmt": "-¥3.6M",
        "ebit": -3567000.0,
        "ebit_fmt": "-¥3.6M",
        "net_income": -7884000.0,
        "net_income_fmt": "-¥7.9M",
        "eps": -1.35,
        "operating_margin": -0.72,
        "total_assets": 768102000.0,
        "total_assets_fmt": "¥8億",
        "total_equity": 729880000.0,
        "total_equity_fmt": "¥7億",
        "total_debt": 0,
        "total_debt_fmt": "N/A",
        "total_cash": 578443000.0,
        "total_cash_fmt": "¥6億",
        "equity_ratio": 95.02,
        "de_ratio": 0.0,
        "current_ratio": 18.27,
        "operating_cf": -18776000.0,
        "operating_cf_fmt": "-¥18.8M",
        "investing_cf": -9273000.0,
        "investing_cf_fmt": "-¥9.3M",
        "financing_cf": 186854000.0,
        "financing_cf_fmt": "¥2億",
        "free_cf": -28049000.0,
        "free_cf_fmt": "-¥28.0M",
        "net_margin": -1.6,
        "roe": -1.08,
        "roa": -1.03
      },
      {
        "year": 2023,
        "revenue": 389705000.0,
        "revenue_fmt": "¥4億",
        "gross_profit": 284062000.0,
        "gross_profit_fmt": "¥3億",
        "operating_income": -23169000.0,
        "operating_income_fmt": "-¥23.2M",
        "ebit": -23169000.0,
        "ebit_fmt": "-¥23.2M",
        "net_income": -28591000.0,
        "net_income_fmt": "-¥28.6M",
        "eps": -5.15,
        "operating_margin": -5.95,
        "total_assets": 591353000.0,
        "total_assets_fmt": "¥6億",
        "total_equity": 548841000.0,
        "total_equity_fmt": "¥5億",
        "total_debt": 0,
        "total_debt_fmt": "N/A",
        "total_cash": 416506000.0,
        "total_cash_fmt": "¥4億",
        "equity_ratio": 92.81,
        "de_ratio": 0.0,
        "current_ratio": 11.86,
        "operating_cf": 1435000.0,
        "operating_cf_fmt": "¥1.4M",
        "investing_cf": -55918000.0,
        "investing_cf_fmt": "-¥55.9M",
        "financing_cf": -23000.0,
        "financing_cf_fmt": "-¥23,000",
        "free_cf": -17612000.0,
        "free_cf_fmt": "-¥17.6M",
        "net_margin": -7.34,
        "roe": -5.21,
        "roa": -4.83
      },
      {
        "year": 2022,
        "revenue": 382688000.0,
        "revenue_fmt": "¥4億",
        "gross_profit": 273043000.0,
        "gross_profit_fmt": "¥3億",
        "operating_income": 25677000.0,
        "operating_income_fmt": "¥25.7M",
        "ebit": 25677000.0,
        "ebit_fmt": "¥25.7M",
        "net_income": 29023000.0,
        "net_income_fmt": "¥29.0M",
        "eps": 5.27,
        "operating_margin": 6.71,
        "total_assets": 599459000.0,
        "total_assets_fmt": "¥6億",
        "total_equity": 568492000.0,
        "total_equity_fmt": "¥6億",
        "total_debt": 0,
        "total_debt_fmt": "N/A",
        "total_cash": 470602000.0,
        "total_cash_fmt": "¥5億",
        "equity_ratio": 94.83,
        "de_ratio": 0.0,
        "current_ratio": 17.77,
        "operating_cf": 16359000.0,
        "operating_cf_fmt": "¥16.4M",
        "investing_cf": -4607000.0,
        "investing_cf_fmt": "-¥4.6M",
        "financing_cf": 3606000.0,
        "financing_cf_fmt": "¥3.6M",
        "free_cf": 11752000.0,
        "free_cf_fmt": "¥11.8M",
        "net_margin": 7.58,
        "roe": 5.11,
        "roa": 4.84
      },
      {
        "year": 2021,
        "revenue": 260356000.0,
        "revenue_fmt": "¥3億",
        "gross_profit": 182678000.0,
        "gross_profit_fmt": "¥2億",
        "operating_income": -64443000.0,
        "operating_income_fmt": "-¥64.4M",
        "ebit": -64443000.0,
        "ebit_fmt": "-¥64.4M",
        "net_income": -62150000.0,
        "net_income_fmt": "-¥62.1M",
        "eps": 0,
        "operating_margin": -24.75,
        "total_assets": 544524000.0,
        "total_assets_fmt": "¥5億",
        "total_equity": 506681000.0,
        "total_equity_fmt": "¥5億",
        "total_debt": 0,
        "total_debt_fmt": "N/A",
        "total_cash": 451874000.0,
        "total_cash_fmt": "¥5億",
        "equity_ratio": 93.05,
        "de_ratio": 0.0,
        "current_ratio": 13.43,
        "operating_cf": -6238000.0,
        "operating_cf_fmt": "-¥6.2M",
        "investing_cf": -5830000.0,
        "investing_cf_fmt": "-¥5.8M",
        "financing_cf": 43120000.0,
        "financing_cf_fmt": "¥43.1M",
        "free_cf": -12068000.0,
        "free_cf_fmt": "-¥12.1M",
        "net_margin": -23.87,
        "roe": -12.27,
        "roa": -11.41
      }
    ],
    "has_data": true
  },
  "dividends": {
    "history": [],
    "has_data": false
  }
}