{
  "success": true,
  "fetched_at": "2026-02-01T03:00:07.604992",
  "ticker": "8159",
  "ticker_full": "8159.T",
  "company_name": "TACHIBANA ELETECH CO LTD.",
  "company_info": {
    "name_en": "TACHIBANA ELETECH CO LTD.",
    "long_name": "Tachibana Eletech Co., Ltd.",
    "sector": "Technology",
    "industry": "Electronic Components",
    "website": "https://www.tachibana.co.jp",
    "employees": 1478,
    "country": "Japan",
    "city": "Osaka",
    "address": "1-13-25, Nishi-Honmachi",
    "description": "Tachibana Eletech Co., Ltd. operates as a technology-driven trading company in Japan and internationally. It operates through Factory Automation System, Semiconductors Device Business, and Facility Business segments. The Factory Automation Systems segment sells programmable controllers, inverters, AC servos, motors, power distribution control devices, industrial robot, electric discharge machines, laser processing machines, connectors, embedded devices, industrial computers, and touch panel monitors. The Semiconductors and Electronic Devices segment offers microcontrollers, ASICs, power modules, memory, analog ICs, and logic ICs, as well as memory cards, contact image sensors, liquid crystals. The Facility Business provides package air conditioners and other air conditioning equipment, LED lighting, solar power generation systems, all-electric appliances, room air conditioners, elevators, substation equipment, and monitoring and control equipment. The company was formerly known as Tachibana Shokai Ltd. and changed its name to Tachibana Eletech Co., Ltd. in September 2001. Tachibana Eletech Co., Ltd. was founded in 1921 and is headquartered in Osaka, Japan."
  },
  "price_trend": {
    "ma_5": {
      "ma_value": 3043.0,
      "deviation": 0.07,
      "trend": "up"
    },
    "ma_25": {
      "ma_value": 3107.2,
      "deviation": -2.0,
      "trend": "down"
    },
    "ma_75": {
      "ma_value": 2967.81,
      "deviation": 2.6,
      "trend": "up"
    },
    "ma_200": {
      "ma_value": 2759.45,
      "deviation": 10.35,
      "trend": "up"
    }
  },
  "financials": {
    "years": [
      {
        "year": 2025,
        "revenue": 220112000000.0,
        "revenue_fmt": "¥2201億",
        "gross_profit": 29328000000.0,
        "gross_profit_fmt": "¥293億",
        "operating_income": 8225000000.0,
        "operating_income_fmt": "¥82億",
        "ebit": 10441000000.0,
        "ebit_fmt": "¥104億",
        "net_income": 7046000000.0,
        "net_income_fmt": "¥70億",
        "eps": 299.74,
        "operating_margin": 3.74,
        "total_assets": 165416000000.0,
        "total_assets_fmt": "¥1654億",
        "total_equity": 94991000000.0,
        "total_equity_fmt": "¥950億",
        "total_debt": 10517000000.0,
        "total_debt_fmt": "¥105億",
        "total_cash": 24069000000.0,
        "total_cash_fmt": "¥241億",
        "equity_ratio": 57.43,
        "de_ratio": 0.11,
        "current_ratio": 2.26,
        "operating_cf": 16462000000.0,
        "operating_cf_fmt": "¥165億",
        "investing_cf": -830000000.0,
        "investing_cf_fmt": "-¥8億",
        "financing_cf": -9348000000.0,
        "financing_cf_fmt": "-¥93億",
        "free_cf": 15568000000.0,
        "free_cf_fmt": "¥156億",
        "net_margin": 3.2,
        "roe": 7.42,
        "roa": 4.26
      },
      {
        "year": 2024,
        "revenue": 231042000000.0,
        "revenue_fmt": "¥2310億",
        "gross_profit": 31765000000.0,
        "gross_profit_fmt": "¥318億",
        "operating_income": 10766000000.0,
        "operating_income_fmt": "¥108億",
        "ebit": 11927000000.0,
        "ebit_fmt": "¥119億",
        "net_income": 8471000000.0,
        "net_income_fmt": "¥85億",
        "eps": 347.27,
        "operating_margin": 4.66,
        "total_assets": 178281000000.0,
        "total_assets_fmt": "¥1783億",
        "total_equity": 92571000000.0,
        "total_equity_fmt": "¥926億",
        "total_debt": 14600000000.0,
        "total_debt_fmt": "¥146億",
        "total_cash": 14945000000.0,
        "total_cash_fmt": "¥149億",
        "equity_ratio": 51.92,
        "de_ratio": 0.16,
        "current_ratio": 1.92,
        "operating_cf": 2126000000.0,
        "operating_cf_fmt": "¥21億",
        "investing_cf": -1289000000.0,
        "investing_cf_fmt": "-¥13億",
        "financing_cf": 2272000000.0,
        "financing_cf_fmt": "¥23億",
        "free_cf": 718000000.0,
        "free_cf_fmt": "¥7億",
        "net_margin": 3.67,
        "roe": 9.15,
        "roa": 4.75
      },
      {
        "year": 2023,
        "revenue": 227266000000.0,
        "revenue_fmt": "¥2273億",
        "gross_profit": 30901000000.0,
        "gross_profit_fmt": "¥309億",
        "operating_income": 10320000000.0,
        "operating_income_fmt": "¥103億",
        "ebit": 11095000000.0,
        "ebit_fmt": "¥111億",
        "net_income": 7841000000.0,
        "net_income_fmt": "¥78億",
        "eps": 313.91,
        "operating_margin": 4.54,
        "total_assets": 153635000000.0,
        "total_assets_fmt": "¥1536億",
        "total_equity": 84639000000.0,
        "total_equity_fmt": "¥846億",
        "total_debt": 6881000000.0,
        "total_debt_fmt": "¥69億",
        "total_cash": 11596000000.0,
        "total_cash_fmt": "¥116億",
        "equity_ratio": 55.09,
        "de_ratio": 0.08,
        "current_ratio": 1.89,
        "operating_cf": -285000000.0,
        "operating_cf_fmt": "-¥3億",
        "investing_cf": 210000000.0,
        "investing_cf_fmt": "¥2億",
        "financing_cf": 88000000.0,
        "financing_cf_fmt": "¥88.0M",
        "free_cf": -681000000.0,
        "free_cf_fmt": "-¥7億",
        "net_margin": 3.45,
        "roe": 9.26,
        "roa": 5.1
      },
      {
        "year": 2022,
        "revenue": 193431000000.0,
        "revenue_fmt": "¥1934億",
        "gross_profit": 25926000000.0,
        "gross_profit_fmt": "¥259億",
        "operating_income": 6713000000.0,
        "operating_income_fmt": "¥67億",
        "ebit": 7536000000.0,
        "ebit_fmt": "¥75億",
        "net_income": 5144000000.0,
        "net_income_fmt": "¥51億",
        "eps": 204.16,
        "operating_margin": 3.47,
        "total_assets": 135172000000.0,
        "total_assets_fmt": "¥1352億",
        "total_equity": 77239000000.0,
        "total_equity_fmt": "¥772億",
        "total_debt": 5047000000.0,
        "total_debt_fmt": "¥50億",
        "total_cash": 11223000000.0,
        "total_cash_fmt": "¥112億",
        "equity_ratio": 57.14,
        "de_ratio": 0.07,
        "current_ratio": 1.94,
        "operating_cf": -7595000000.0,
        "operating_cf_fmt": "-¥76億",
        "investing_cf": -968000000.0,
        "investing_cf_fmt": "-¥10億",
        "financing_cf": 702000000.0,
        "financing_cf_fmt": "¥7億",
        "free_cf": -8375000000.0,
        "free_cf_fmt": "-¥84億",
        "net_margin": 2.66,
        "roe": 6.66,
        "roa": 3.81
      },
      {
        "year": 2021,
        "revenue": 0,
        "revenue_fmt": "N/A",
        "gross_profit": 0,
        "gross_profit_fmt": "N/A",
        "operating_income": 0,
        "operating_income_fmt": "N/A",
        "ebit": 0,
        "ebit_fmt": "N/A",
        "net_income": 0,
        "net_income_fmt": "N/A",
        "eps": 0,
        "operating_margin": 0,
        "total_assets": 0,
        "total_assets_fmt": "N/A",
        "total_equity": 0,
        "total_equity_fmt": "N/A",
        "total_debt": 0,
        "total_debt_fmt": "N/A",
        "total_cash": 0,
        "total_cash_fmt": "N/A",
        "equity_ratio": 0,
        "de_ratio": 0,
        "current_ratio": 0,
        "operating_cf": 0,
        "operating_cf_fmt": "N/A",
        "investing_cf": 0,
        "investing_cf_fmt": "N/A",
        "financing_cf": 0,
        "financing_cf_fmt": "N/A",
        "free_cf": 0,
        "free_cf_fmt": "N/A",
        "net_margin": 0,
        "roe": 0,
        "roa": 0
      }
    ],
    "has_data": true
  },
  "dividends": {
    "history": [
      {
        "year": 2021,
        "amount": 50.0
      },
      {
        "year": 2022,
        "amount": 70.0
      },
      {
        "year": 2023,
        "amount": 100.0
      },
      {
        "year": 2024,
        "amount": 100.0
      },
      {
        "year": 2025,
        "amount": 100.0
      }
    ],
    "latest": 50.0,
    "has_data": true
  }
}